schemadiff/__init__.py
schemadiff/__main__.py
schemadiff/allow_list.py
schemadiff/formatting.py
schemadiff/schema_loader.py
schemadiff/validation.py
schemadiff/changes/__init__.py
schemadiff/changes/argument.py
schemadiff/changes/directive.py
schemadiff/changes/enum.py
schemadiff/changes/field.py
schemadiff/changes/input.py
schemadiff/changes/interface.py
schemadiff/changes/object.py
schemadiff/changes/schema.py
schemadiff/changes/type.py
schemadiff/changes/union.py
schemadiff/diff/__init__.py
schemadiff/diff/argument.py
schemadiff/diff/directive.py
schemadiff/diff/enum.py
schemadiff/diff/field.py
schemadiff/diff/input_object_type.py
schemadiff/diff/interface.py
schemadiff/diff/object_type.py
schemadiff/diff/schema.py
schemadiff/diff/union_type.py
schemadiff/validation_rules/__init__.py
graphql_schema_diff-1.2.4.dist-info/METADATA
graphql_schema_diff-1.2.4.dist-info/WHEEL
graphql_schema_diff-1.2.4.dist-info/entry_points.txt
graphql_schema_diff-1.2.4.dist-info/licenses/LICENSE
graphql_schema_diff-1.2.4.dist-info/RECORD
