Metadata-Version: 2.1
Name: graphql-schema-diff
Version: 1.2.4
Summary: Compare GraphQL Schemas
Project-URL: Homepage, https://github.com/Ambro17/graphql-schema-diff
Project-URL: Documentation, https://ambro17.github.io/graphql-schema-diff/
Author-email: Nahuel Ambrosini <ambro17.1@gmail.com>
License-Expression: GPL-3.0-or-later
License-File: LICENSE
Classifier: License :: OSI Approved :: GNU General Public License v3 (GPLv3)
Classifier: Operating System :: OS Independent
Classifier: Programming Language :: Python :: 3
Requires-Python: >=3.6
Requires-Dist: attrs>=19.3.0
Requires-Dist: graphql-core>=3.0.1
Provides-Extra: dev
Requires-Dist: codecov; extra == 'dev'
Requires-Dist: flake8; extra == 'dev'
Requires-Dist: hatch; extra == 'dev'
Requires-Dist: pdoc3==0.9.1; extra == 'dev'
Requires-Dist: pytest; extra == 'dev'
Requires-Dist: pytest-cov; extra == 'dev'
